pdf_namer/__init__.py
pdf_namer/main.py
pdf_namer/pdf_namer.py
pdf_namer-0.3.4.dist-info/LICENSE.md
pdf_namer-0.3.4.dist-info/METADATA
pdf_namer-0.3.4.dist-info/WHEEL
pdf_namer-0.3.4.dist-info/entry_points.txt
pdf_namer-0.3.4.dist-info/top_level.txt
pdf_namer-0.3.4.dist-info/RECORD
