Metadata-Version: 2.1
Name: pdf-namer
Version: 0.3.4
Summary: A Linux-specific tool for naming PDF files
Home-page: https://github.com/llabusch93/pdf-namer
Author: Laurence Labusch
Author-email: laurence.labusch@gmail.com
Classifier: Programming Language :: Python :: 3
Classifier: License :: OSI Approved :: MIT License
Classifier: Operating System :: POSIX :: Linux
Requires-Python: >=3.6
License-File: LICENSE.md
Requires-Dist: pydantic>=2.9.0
Requires-Dist: openai>=1.50.0
Requires-Dist: PyPDF2>=3.0.1
Requires-Dist: toml>=0.10.2
Requires-Dist: pycryptodome>=3.19.0
